pricat/__init__.py
pricat/file.py
pricat/list.py
pricat-0.1.2.dist-info/LICENSE
pricat-0.1.2.dist-info/METADATA
pricat-0.1.2.dist-info/WHEEL
pricat-0.1.2.dist-info/top_level.txt
pricat-0.1.2.dist-info/RECORD
