Metadata-Version: 2.1
Name: pricat
Version: 0.1.2
Summary: pricat is a simple utility for parsing tire lists files in the PRICAT format
Home-page: https://gitlab.com/matteo.redaelli/pricat.py
Author: Matteo Redaelli
Author-email: matteo.redaelli@gmail.com
License: UNKNOWN
Platform: UNKNOWN
Classifier: Programming Language :: Python :: 3
Classifier: Operating System :: OS Independent
Requires-Python: >=3.5
Requires-Dist: pandas
